Classfile /C:/Users/C00273530/Desktop/Sem2Project/Sem2Project/JavaApplication2/Fibonacci.class
  Last modified 25 Apr 2024; size 390 bytes
  SHA-256 checksum d1d291c30b002d94e29984605fdf2a0fb412e69c8cbfd6256d69cee7579e53ed
  Compiled from "Fibonacci.java"
class Fibonacci
  minor version: 0
  major version: 65
  flags: (0x0020) ACC_SUPER
  this_class: #7                          // Fibonacci
  super_class: #2                         // java/lang/Object
  interfaces: 0, fields: 0, methods: 2, attributes: 1
Constant pool:
   #1 = Methodref          #2.#3          // java/lang/Object."<init>":()V
   #2 = Class              #4             // java/lang/Object
   #3 = NameAndType        #5:#6          // "<init>":()V
   #4 = Utf8               java/lang/Object
   #5 = Utf8               <init>
   #6 = Utf8               ()V
   #7 = Class              #8             // Fibonacci
   #8 = Utf8               Fibonacci
   #9 = Utf8               Code
  #10 = Utf8               LineNumberTable
  #11 = Utf8               main
  #12 = Utf8               ([Ljava/lang/String;)V
  #13 = Utf8               StackMapTable
  #14 = Class              #15            // "[I"
  #15 = Utf8               [I
  #16 = Utf8               SourceFile
  #17 = Utf8               Fibonacci.java
{
  Fibonacci();
    descriptor: ()V
    flags: (0x0000)
    Code:
      stack=1, locals=1, args_size=1
         0: aload_0
         1: invokespecial #1                  // Method java/lang/Object."<init>":()V
         4: return
      LineNumberTable:
        line 1: 0

  public static void main(java.lang.String[]);
    descriptor: ([Ljava/lang/String;)V
    flags: (0x0009) ACC_PUBLIC, ACC_STATIC
    Code:
      stack=4, locals=4, args_size=1
         0: bipush        8
         2: newarray       int
         4: dup
         5: iconst_0
         6: iconst_1
         7: iastore
         8: dup
         9: iconst_1
        10: iconst_1
        11: iastore
        12: dup
        13: iconst_2
        14: iconst_2
        15: iastore
        16: dup
        17: iconst_3
        18: iconst_3
        19: iastore
        20: dup
        21: iconst_4
        22: iconst_5
        23: iastore
        24: dup
        25: iconst_5
        26: bipush        8
        28: iastore
        29: dup
        30: bipush        6
        32: bipush        13
        34: iastore
        35: dup
        36: bipush        7
        38: bipush        21
        40: iastore
        41: astore_1
        42: iconst_0
        43: istore_2
        44: iconst_0
        45: istore_3
        46: iload_3
        47: aload_1
        48: arraylength
        49: if_icmpge     64
        52: iload_2
        53: aload_1
        54: iload_3
        55: iaload
        56: iadd
        57: istore_2
        58: iinc          3, 1
        61: goto          46
        64: return
      LineNumberTable:
        line 4: 0
        line 5: 42
        line 6: 44
        line 7: 52
        line 6: 58
        line 9: 64
      StackMapTable: number_of_entries = 2
        frame_type = 254 /* append */
          offset_delta = 46
          locals = [ class "[I", int, int ]
        frame_type = 250 /* chop */
          offset_delta = 17
}
SourceFile: "Fibonacci.java"
