Classfile /C:/Users/C00273530/Desktop/Sem2Project/Sem2Project/JavaApplication2/array.class
  Last modified 20 Apr 2024; size 389 bytes
  SHA-256 checksum 2c8c886d9a0e5763d7f83b110ce04ff30b3e898defb2627f238e6d3faf1ae4ea
  Compiled from "array.java"
class array
  minor version: 0
  major version: 65
  flags: (0x0020) ACC_SUPER
  this_class: #13                         // array
  super_class: #2                         // java/lang/Object
  interfaces: 0, fields: 0, methods: 2, attributes: 1
Constant pool:
   #1 = Methodref          #2.#3          // java/lang/Object."<init>":()V
   #2 = Class              #4             // java/lang/Object
   #3 = NameAndType        #5:#6          // "<init>":()V
   #4 = Utf8               java/lang/Object
   #5 = Utf8               <init>
   #6 = Utf8               ()V
   #7 = Methodref          #8.#9          // java/lang/Integer.valueOf:(I)Ljava/lang/Integer;
   #8 = Class              #10            // java/lang/Integer
   #9 = NameAndType        #11:#12        // valueOf:(I)Ljava/lang/Integer;
  #10 = Utf8               java/lang/Integer
  #11 = Utf8               valueOf
  #12 = Utf8               (I)Ljava/lang/Integer;
  #13 = Class              #14            // array
  #14 = Utf8               array
  #15 = Utf8               Code
  #16 = Utf8               LineNumberTable
  #17 = Utf8               main
  #18 = Utf8               ([Ljava/lang/String;)V
  #19 = Utf8               SourceFile
  #20 = Utf8               array.java
{
  array();
    descriptor: ()V
    flags: (0x0000)
    Code:
      stack=1, locals=1, args_size=1
         0: aload_0
         1: invokespecial #1                  // Method java/lang/Object."<init>":()V
         4: return
      LineNumberTable:
        line 1: 0

  public static void main(java.lang.String[]);
    descriptor: ([Ljava/lang/String;)V
    flags: (0x0009) ACC_PUBLIC, ACC_STATIC
    Code:
      stack=3, locals=2, args_size=1
         0: iconst_5
         1: anewarray     #2                  // class java/lang/Object
         4: astore_1
         5: aload_1
         6: iconst_0
         7: iconst_3
         8: invokestatic  #7                  // Method java/lang/Integer.valueOf:(I)Ljava/lang/Integer;
        11: aastore
        12: aload_1
        13: iconst_1
        14: iconst_2
        15: invokestatic  #7                  // Method java/lang/Integer.valueOf:(I)Ljava/lang/Integer;
        18: aastore
        19: aload_1
        20: iconst_2
        21: iconst_5
        22: invokestatic  #7                  // Method java/lang/Integer.valueOf:(I)Ljava/lang/Integer;
        25: aastore
        26: aload_1
        27: iconst_3
        28: bipush        32
        30: invokestatic  #7                  // Method java/lang/Integer.valueOf:(I)Ljava/lang/Integer;
        33: aastore
        34: aload_1
        35: iconst_4
        36: bipush        11
        38: invokestatic  #7                  // Method java/lang/Integer.valueOf:(I)Ljava/lang/Integer;
        41: aastore
        42: return
      LineNumberTable:
        line 3: 0
        line 4: 5
        line 5: 12
        line 6: 19
        line 7: 26
        line 8: 34
        line 10: 42
}
SourceFile: "array.java"
